odoo10_addon_web_no_bubble-10.0.1.0.0-py2.7-nspkg.pth
odoo/addons/web_no_bubble/__manifest__.py
odoo/addons/web_no_bubble/__init__.py
odoo/addons/web_no_bubble/README.rst
odoo/addons/web_no_bubble/views/web_no_bubble.xml
odoo/addons/web_no_bubble/static/description/icon.png
odoo/addons/web_no_bubble/static/src/css/web_no_bubble.css
odoo10_addon_web_no_bubble-10.0.1.0.0.dist-info/top_level.txt
odoo10_addon_web_no_bubble-10.0.1.0.0.dist-info/WHEEL
odoo10_addon_web_no_bubble-10.0.1.0.0.dist-info/RECORD
odoo10_addon_web_no_bubble-10.0.1.0.0.dist-info/metadata.json
odoo10_addon_web_no_bubble-10.0.1.0.0.dist-info/DESCRIPTION.rst
odoo10_addon_web_no_bubble-10.0.1.0.0.dist-info/METADATA
odoo10_addon_web_no_bubble-10.0.1.0.0.dist-info/namespace_packages.txt
